pysizer/__init__.py
pysizer/cli.py
PySizer-1.0.0.dist-info/LICENSE.md
PySizer-1.0.0.dist-info/METADATA
PySizer-1.0.0.dist-info/WHEEL
PySizer-1.0.0.dist-info/entry_points.txt
PySizer-1.0.0.dist-info/top_level.txt
PySizer-1.0.0.dist-info/RECORD
