Metadata-Version: 2.1
Name: PySizer
Version: 1.0.0
Summary: Quick & Efficient Command Line picture resizer!
Home-page: https://github.com/kumaraditya303/PySizer
Author: Kumar Aditya
Author-email: 
License: MIT
Keywords: Pillow ThreadPoolExecutor
Platform: UNKNOWN
Classifier: Programming Language :: Python
Classifier: Programming Language :: Python :: 3
Classifier: Programming Language :: Python :: 3.7
Classifier: Programming Language :: Python :: 3.8
Classifier: Programming Language :: Python :: 3.9
Classifier: Programming Language :: Python :: 3 :: Only
Classifier: Operating System :: OS Independent
Classifier: License :: OSI Approved :: MIT License
Classifier: Topic :: Utilities
Requires-Python: >=3.7
Requires-Dist: Pillow (==8.1.0)
Requires-Dist: click (==7.1.2)
Provides-Extra: tests
Requires-Dist: pre-commit (==2.9.3) ; extra == 'tests'
Requires-Dist: pytest (==6.2.1) ; extra == 'tests'
Requires-Dist: pytest-cov (==2.11.1) ; extra == 'tests'
